[
  {
    "description": "Daily Vitamin D3 supplement",
    "medicineName": "Vitamin D3",
    "reminderMessage": "This is a friendly reminder to take your medicine tomorrow. Please don\u0027t forget!",
    "reminderDate": "2026-08-10",
    "reminderTime": "09:00"
  },
  {
    "description": "Blood pressure tablet",
    "medicineName": "Amlodipine",
    "reminderMessage": "Don\u0027t forget to take your blood pressure tablet tomorrow!",
    "reminderDate": "2026-07-20",
    "reminderTime": "09:00"
  }
]